interaktiv/__init__.py
interaktiv/alttexts/__init__.py
interaktiv/alttexts/configure.zcml
interaktiv/alttexts/dependencies.zcml
interaktiv/alttexts/interfaces.py
interaktiv/alttexts/profiles.zcml
interaktiv/alttexts/testing.py
interaktiv/alttexts/behaviors/__init__.py
interaktiv/alttexts/behaviors/alt_text.py
interaktiv/alttexts/behaviors/configure.zcml
interaktiv/alttexts/browser/__init__.py
interaktiv/alttexts/browser/configure.zcml
interaktiv/alttexts/browser/templates/image.pt
interaktiv/alttexts/indexers/__init__.py
interaktiv/alttexts/indexers/alt_text.py
interaktiv/alttexts/indexers/configure.zcml
interaktiv/alttexts/locales/__init__.py
interaktiv/alttexts/locales/__main__.py
interaktiv/alttexts/locales/interaktiv.alttexts.pot
interaktiv/alttexts/locales/de/LC_MESSAGES/interaktiv.alttexts.po
interaktiv/alttexts/locales/en/LC_MESSAGES/interaktiv.alttexts.po
interaktiv/alttexts/profiles/default/browserlayer.xml
interaktiv/alttexts/profiles/default/catalog.xml
interaktiv/alttexts/profiles/default/metadata.xml
interaktiv/alttexts/profiles/default/registry/main.xml
interaktiv/alttexts/profiles/default/types/.gitkeep
interaktiv/alttexts/profiles/default/types/Image.xml
interaktiv/alttexts/profiles/uninstall/browserlayer.xml
interaktiv/alttexts/profiles/uninstall/metadata.xml
interaktiv/alttexts/serializers/__init__.py
interaktiv/alttexts/serializers/configure.zcml
interaktiv/alttexts/serializers/summary.py
interaktiv/alttexts/setuphandlers/__init__.py
interaktiv/alttexts/upgrades/__init__.py
interaktiv/alttexts/upgrades/configure.zcml
interaktiv/alttexts/upgrades/v1_to_v1000.py
interaktiv_alttexts-1.0.0.dist-info/METADATA
interaktiv_alttexts-1.0.0.dist-info/WHEEL
interaktiv_alttexts-1.0.0.dist-info/entry_points.txt
interaktiv_alttexts-1.0.0.dist-info/licenses/LICENSE.md
interaktiv_alttexts-1.0.0.dist-info/RECORD
